{"SPDXID":"SPDXRef-DOCUMENT","creationInfo":{"created":"2026-07-19T00:55:10Z","creators":["Tool: takoform-form-package-release"]},"dataLicense":"CC0-1.0","documentNamespace":"https://forms.takoform.com/spdx/package/20806961e8a48ea2ba1caa1e8819560e3306d44ec80dafe382ba25c2c110a85f","files":[{"SPDXID":"SPDXRef-File-package-index.json-20806961e8a4","checksums":[{"algorithm":"SHA256","checksumValue":"20806961e8a48ea2ba1caa1e8819560e3306d44ec80dafe382ba25c2c110a85f"}],"copyrightText":"NOASSERTION","fileName":"./package-index.json","licenseConcluded":"NOASSERTION","licenseInfoInFiles":["NOASSERTION"]},{"SPDXID":"SPDXRef-File-definition.json-697c856a7a3d","checksums":[{"algorithm":"SHA256","checksumValue":"697c856a7a3dbca7b9bebe7c82990ed46ccd019a964eecd65776a6f0d95c6d70"}],"copyrightText":"NOASSERTION","fileName":"./definition.json","licenseConcluded":"NOASSERTION","licenseInfoInFiles":["NOASSERTION"]},{"SPDXID":"SPDXRef-File-fixtures-desired.json-ff08fe38e266","checksums":[{"algorithm":"SHA256","checksumValue":"ff08fe38e2664273a1cdf392f708169b421f7e128763f4f617182c4218f013f6"}],"copyrightText":"NOASSERTION","fileName":"./fixtures/desired.json","licenseConcluded":"NOASSERTION","licenseInfoInFiles":["NOASSERTION"]},{"SPDXID":"SPDXRef-File-fixtures-negative.json-1c01606ca613","checksums":[{"algorithm":"SHA256","checksumValue":"1c01606ca61367007a7cecf407efed07d2df8f77598ca92d9e3bf76a81d14859"}],"copyrightText":"NOASSERTION","fileName":"./fixtures/negative.json","licenseConcluded":"NOASSERTION","licenseInfoInFiles":["NOASSERTION"]},{"SPDXID":"SPDXRef-File-fixtures-observed.json-4c66ee467560","checksums":[{"algorithm":"SHA256","checksumValue":"4c66ee46756053ba74a07f62b013668c4ec11e3311abb4bc724ef0bd1ad26ea5"}],"copyrightText":"NOASSERTION","fileName":"./fixtures/observed.json","licenseConcluded":"NOASSERTION","licenseInfoInFiles":["NOASSERTION"]},{"SPDXID":"SPDXRef-File-fixtures-output.json-b462d901bcd9","checksums":[{"algorithm":"SHA256","checksumValue":"b462d901bcd91a0ed94a99049850e9741ea56f35747ce9fae5345c2d2620c5d9"}],"copyrightText":"NOASSERTION","fileName":"./fixtures/output.json","licenseConcluded":"NOASSERTION","licenseInfoInFiles":["NOASSERTION"]}],"name":"Takoform Form Package StatefulActorNamespace 1.0.0","packages":[{"SPDXID":"SPDXRef-Package","copyrightText":"NOASSERTION","downloadLocation":"NOASSERTION","filesAnalyzed":true,"licenseConcluded":"NOASSERTION","licenseDeclared":"NOASSERTION","name":"StatefulActorNamespace","packageVerificationCode":{"packageVerificationCodeValue":"54bf73a4bf78b8a62cffca59b0d53092130b78cc"},"versionInfo":"1.0.0"}],"relationships":[{"relatedSpdxElement":"SPDXRef-Package","relationshipType":"DESCRIBES","spdxElementId":"SPDXRef-DOCUMENT"},{"relatedSpdxElement":"SPDXRef-File-package-index.json-20806961e8a4","relationshipType":"CONTAINS","spdxElementId":"SPDXRef-Package"},{"relatedSpdxElement":"SPDXRef-File-definition.json-697c856a7a3d","relationshipType":"CONTAINS","spdxElementId":"SPDXRef-Package"},{"relatedSpdxElement":"SPDXRef-File-fixtures-desired.json-ff08fe38e266","relationshipType":"CONTAINS","spdxElementId":"SPDXRef-Package"},{"relatedSpdxElement":"SPDXRef-File-fixtures-negative.json-1c01606ca613","relationshipType":"CONTAINS","spdxElementId":"SPDXRef-Package"},{"relatedSpdxElement":"SPDXRef-File-fixtures-observed.json-4c66ee467560","relationshipType":"CONTAINS","spdxElementId":"SPDXRef-Package"},{"relatedSpdxElement":"SPDXRef-File-fixtures-output.json-b462d901bcd9","relationshipType":"CONTAINS","spdxElementId":"SPDXRef-Package"}],"spdxVersion":"SPDX-2.3"}